Metadata-Version: 2.1
Name: pythonbq
Version: 1.0.0
Summary: Python wrapper for easy use of big query
Home-page: https://github.com/connor-makowski/pythonbq
Download-URL: https://github.com/connor-makowski/pythonbq/dist/pythonbq-1.0.0.tar.gz
Author: Connor Makowski
Author-email: connor.m.makowski@gmail.com
License: MIT
Keywords: bigquery,big,query,pythonbq
Classifier: Development Status :: 3 - Alpha
Classifier: Intended Audience :: Developers
Classifier: Topic :: Software Development :: Build Tools
Classifier: License :: OSI Approved :: MIT License
Classifier: Programming Language :: Python :: 3
License-File: LICENSE
